vana/__init__.py
vana/chain_data.py
vana/chain_manager.py
vana/cli.py
vana/client.py
vana/commands/__init__.py
vana/commands/base_command.py
vana/commands/satya.py
vana/commands/transfer.py
vana/commands/wallets.py
vana/config.py
vana/contracts/ComputeEngine.json
vana/contracts/ComputeEngineTeePool.json
vana/contracts/ComputeInstructionRegistry.json
vana/contracts/DataRefinerRegistry.json
vana/contracts/DataRegistry.json
vana/contracts/QueryEngine.json
vana/contracts/RootNetworkContract.json
vana/contracts/TeePool.json
vana/contracts/__init__.py
vana/contracts/__main__.py
vana/errors.py
vana/keyfile.py
vana/logging/__init__.py
vana/logging/defines.py
vana/logging/format.py
vana/logging/helpers.py
vana/logging/loggingmachine.py
vana/message.py
vana/mock/__init__.py
vana/mock/keyfile_mock.py
vana/mock/wallet_mock.py
vana/node_client.py
vana/node_server.py
vana/state.py
vana/threadpool.py
vana/utils/__init__.py
vana/utils/fast_api_threaded_server.py
vana/utils/misc.py
vana/utils/networking.py
vana/utils/transaction.py
vana/utils/wallet_utils.py
vana/utils/web3.py
vana/wallet.py
vana-0.47.0.dist-info/METADATA
vana-0.47.0.dist-info/WHEEL
vana-0.47.0.dist-info/entry_points.txt
vana-0.47.0.dist-info/RECORD
