Metadata-Version: 2.3
Name: vana
Version: 0.47.0
Summary: 
Author: Tim Nunamaker
Author-email: tim@vana.com
Requires-Python: >=3.10,<3.13
Classifier: Programming Language :: Python :: 3
Classifier: Programming Language :: Python :: 3.10
Classifier: Programming Language :: Python :: 3.11
Classifier: Programming Language :: Python :: 3.12
Requires-Dist: aiohttp (>=3.9.5,<4.0.0)
Requires-Dist: ansible (>=9.5.1,<10.0.0)
Requires-Dist: ansible-vault (>=2.1.0,<3.0.0)
Requires-Dist: colorama (>=0.4.6,<0.5.0)
Requires-Dist: eth-abi (>=5.1.0,<6.0.0)
Requires-Dist: fastapi (>=0.111.0,<0.112.0)
Requires-Dist: munch (>=4.0.0,<5.0.0)
Requires-Dist: netaddr (>=1.2.1,<2.0.0)
Requires-Dist: password-strength (>=0.0.3.post2,<0.0.4)
Requires-Dist: pydantic (>=2.7.1,<3.0.0)
Requires-Dist: pynacl (>=1.5.0,<2.0.0)
Requires-Dist: python-dotenv (>=1.0.1,<2.0.0)
Requires-Dist: python-statemachine (>=2.2.0,<3.0.0)
Requires-Dist: requests (>=2.31.0,<3.0.0)
Requires-Dist: retry (>=0.9.2,<0.10.0)
Requires-Dist: rich (>=13.7.1,<14.0.0)
Requires-Dist: shtab (>=1.7.1,<2.0.0)
Requires-Dist: tomli (>=2.1.0,<3.0.0)
Requires-Dist: uvicorn (>=0.29.0,<0.30.0)
Requires-Dist: web3 (>=6.18.0,<7.0.0)
Project-URL: Repository, https://github.com/vana-com/vana-framework
